senaite.instruments-1.0.0-py3.6-nspkg.pth
senaite/instruments/__init__.py
senaite/instruments/configure.zcml
senaite/instruments/instrument.py
senaite/instruments/instruments/__init__.py
senaite/instruments/instruments/configure.zcml
senaite/instruments/instruments/agilent/__init__.py
senaite/instruments/instruments/agilent/chemstation/__init__.py
senaite/instruments/instruments/agilent/chemstation/chemstation.py
senaite/instruments/instruments/agilent/chemstation/chemstation_import.pt
senaite/instruments/instruments/agilent/masshunter/__init__.py
senaite/instruments/instruments/agilent/masshunter/aorc.py
senaite/instruments/instruments/agilent/masshunter/aorc_import.pt
senaite/instruments/instruments/agilent/masshunter/qualitative.py
senaite/instruments/instruments/agilent/masshunter/qualitative_import.pt
senaite/instruments/instruments/agilent/masshunter/quantitative.py
senaite/instruments/instruments/agilent/masshunter/quantitative_import.pt
senaite/instruments/instruments/bruker/__init__.py
senaite/instruments/instruments/bruker/s8tiger/__init__.py
senaite/instruments/instruments/bruker/s8tiger/s8tiger.md
senaite/instruments/instruments/bruker/s8tiger/s8tiger.py
senaite/instruments/instruments/bruker/s8tiger/s8tiger_import.pt
senaite/instruments/instruments/perkinelmer/__init__.py
senaite/instruments/instruments/perkinelmer/nexion350x/__init__.py
senaite/instruments/instruments/perkinelmer/nexion350x/nexion350x.md
senaite/instruments/instruments/perkinelmer/nexion350x/nexion350x.py
senaite/instruments/instruments/perkinelmer/nexion350x/nexion350x_import.pt
senaite/instruments/instruments/perkinelmer/winlab32/__init__.py
senaite/instruments/instruments/perkinelmer/winlab32/winlab32.md
senaite/instruments/instruments/perkinelmer/winlab32/winlab32.py
senaite/instruments/instruments/perkinelmer/winlab32/winlab32_import.pt
senaite/instruments/instruments/xcalibur/__init__.py
senaite/instruments/instruments/xcalibur/instrument.py
senaite.instruments-1.0.0.dist-info/LICENSE
senaite.instruments-1.0.0.dist-info/METADATA
senaite.instruments-1.0.0.dist-info/WHEEL
senaite.instruments-1.0.0.dist-info/entry_points.txt
senaite.instruments-1.0.0.dist-info/namespace_packages.txt
senaite.instruments-1.0.0.dist-info/top_level.txt
senaite.instruments-1.0.0.dist-info/RECORD
