Metadata-Version: 2.1
Name: senaite.instruments
Version: 1.0.0
Summary: Import and export instrument adapters for SENAITE
Home-page: https://github.com/senaite/senaite.instruments
Author: SENAITE Foundation
Author-email: hello@senaite.com
License: GPLv2
Platform: UNKNOWN
Classifier: Framework :: Plone
Classifier: Framework :: Zope2
Classifier: Programming Language :: Python
Classifier: Development Status :: 5 - Production/Stable
Classifier: License :: OSI Approved :: GNU General Public License v2 (GPLv2)
License-File: LICENSE
Requires-Dist: setuptools
Requires-Dist: senaite.api
Requires-Dist: senaite.core
Requires-Dist: xlrd
Requires-Dist: openpyxl (==2.6.4)
Provides-Extra: test
Requires-Dist: Products.PloneTestCase ; extra == 'test'
Requires-Dist: plone.app.testing ; extra == 'test'
Requires-Dist: robotsuite ; extra == 'test'
Requires-Dist: unittest2 ; extra == 'test'
